dateutils/__init__.py
dateutils/dateadd.py
dateutils/datediff.py
dateutils-0.6.11.dist-info/LICENSE
dateutils-0.6.11.dist-info/METADATA
dateutils-0.6.11.dist-info/WHEEL
dateutils-0.6.11.dist-info/entry_points.txt
dateutils-0.6.11.dist-info/top_level.txt
dateutils-0.6.11.dist-info/RECORD
