Metadata-Version: 2.1
Name: dateutils
Version: 0.6.11
Summary: Various utilities for working with date and datetime objects
Home-page: https://github.com/jmcantrell/python-dateutils
Author: Jeremy Cantrell
Author-email: jmcantrell@gmail.com
License: UNKNOWN
Platform: UNKNOWN
Classifier: Development Status :: 4 - Beta
Classifier: Intended Audience :: Developers
Classifier: License :: OSI Approved :: BSD License
Classifier: Natural Language :: English
Classifier: Operating System :: POSIX :: Linux
Classifier: Programming Language :: Python
